CHANGELOG.md
CLA.md
CODE_OF_CONDUCT.md
CONTRIBUTING.md
MANIFEST.in
README.md
RELEASE_NOTES.md
requirements-test.txt
requirements.txt
setup.cfg
setup.py
muptick/__init__.py
muptick/account.py
muptick/api.py
muptick/callorders.py
muptick/cli.py
muptick/committee.py
muptick/decorators.py
muptick/feed.py
muptick/htlc.py
muptick/info.py
muptick/main.py
muptick/markets.py
muptick/message.py
muptick/proposal.py
muptick/rpc.py
muptick/tools.py
muptick/ui.py
muptick/vesting.py
muptick/votes.py
muptick/wallet.py
muptick/witness.py
muptick/workers.py
muptick.egg-info/PKG-INFO
muptick.egg-info/SOURCES.txt
muptick.egg-info/dependency_links.txt
muptick.egg-info/entry_points.txt
muptick.egg-info/requires.txt
muptick.egg-info/top_level.txt
muptick/apis/example-config.yaml
muptick/apis/poloniex.py