Metadata-Version: 1.2
Name: muptick
Version: 0.2.3
Summary: Command line tool to interface with the Meta1 network
Home-page: http://muptick.rocks
Author: Fabian Schuh
Author-email: Fabian@chainsquad.com
Maintainer: Fabian Schuh
Maintainer-email: Fabian@chainsquad.com
License: UNKNOWN
Download-URL: https://github.com/xeroc/muptick/tarball/0.2.3
Keywords: meta1,library,api,rpc,cli
Platform: UNKNOWN
Classifier: License :: OSI Approved :: MIT License
Classifier: Operating System :: OS Independent
Classifier: Programming Language :: Python :: 3
Classifier: Development Status :: 3 - Alpha
Classifier: Intended Audience :: Developers
